test/gmswritertests/test_gms_output.py
test/gmswritertests/test_gms_writer.py
test/gmswritertests/__init__.py
test/unittests/test_AttenN.py
test/unittests/test_UrbanQTotal_1.py
test/unittests/test_NSTAB.py
test/unittests/test_RetentFactorN.py
test/unittests/test_GRLoadN.py
test/unittests/test_RuralQTotal.py
test/unittests/test_NGLostManN.py
test/unittests/test_BSed.py
test/unittests/test_UnSatStorCarryover.py
test/unittests/test_StreamBankNSum.py
test/unittests/test_AvGroundWater.py
test/unittests/test_NRUNCON_2.py
test/unittests/test_NGAccManAppN.py
test/unittests/test_GRLostBarnN.py
test/unittests/test_NAWMSL.py
test/unittests/test_QTotal.py
test/unittests/test_CNumImperv.py
test/unittests/test_NGAppManN.py
test/unittests/test_AvSedYield.py
test/unittests/test_SedYield_1.py
test/unittests/test_Rain.py
test/unittests/test_StreamBankN_1.py
test/unittests/test_LE.py
test/unittests/test_FilterEff.py
test/unittests/test_AgRunoff.py
test/unittests/test_CNumImpervReten.py
test/unittests/test_RetentionEff.py
test/unittests/test_GRAccManAppN.py
test/unittests/test_AgAreaTotal.py
test/unittests/test_Grow.py
test/unittests/test_CNumPervReten.py
test/unittests/test_NGInitBarnN.py
test/unittests/test_CNI.py
test/unittests/test_GRLostManN.py
test/unittests/test_LuDisLoad.py
test/unittests/test_GRLBN.py
test/unittests/test_GRLostBarnNSum.py
test/unittests/test_GrazingAnimal.py
test/unittests/test_UrbanRunoffLiter.py
test/unittests/test_RurEros.py
test/unittests/test_NLU.py
test/unittests/test_RurQRunoff.py
test/unittests/test_AreaTotal.py
test/unittests/test_AvGRLostBarnNSum.py
test/unittests/test_N7b_2.py
test/unittests/test_FlowDays.py
test/unittests/test_DeepSeep.py
test/unittests/test_CNP.py
test/unittests/test_InitNgN.py
test/unittests/test_AGSTRM.py
test/unittests/test_lu.py
test/unittests/test_AvGRLostBarnN.py
test/unittests/test_UrbAreaTotal.py
test/unittests/test_GrFlow.py
test/unittests/test_WashPerv.py
gwlf_e-3.3.0.dist-info/LICENSE
gwlf_e-3.3.0.dist-info/WHEEL
gwlf_e-3.3.0.dist-info/top_level.txt
gwlf_e-3.3.0.dist-info/RECORD
gwlf_e-3.3.0.dist-info/METADATA
