Metadata-Version: 2.1
Name: gwlf-e
Version: 3.3.0
Summary: A Python port of Generalized Watersheds Loading Functions - Enhanced (MapShed)
Home-page: https://github.com/WikiWatershed/gwlf-e
Author: Azavea Inc.
Author-email: systems@azavea.com
License: Apache License 2.0
Keywords: gwlf-e watershed hydrology
Classifier: Development Status :: 5 - Production/Stable
Classifier: Intended Audience :: Developers
Classifier: Intended Audience :: Education
Classifier: License :: OSI Approved :: Apache Software License
Classifier: Programming Language :: Python :: 3
Requires-Python: >=3.7
License-File: LICENSE
Requires-Dist: certifi >=2021
Requires-Dist: funcsigs ==1.0.2
Requires-Dist: llvmlite ==0.38.*
Requires-Dist: pynose ==1.5.*
Requires-Dist: numpy ==1.22.*
Requires-Dist: numba ==0.55.*
Provides-Extra: dev
Provides-Extra: test
Requires-Dist: pynose ==1.5.* ; extra == 'test'
Requires-Dist: coverage ==4.0.3 ; extra == 'test'
